README.md
setup.py
nightscout_python_client/__init__.py
nightscout_python_client/api_client.py
nightscout_python_client/configuration.py
nightscout_python_client/rest.py
nightscout_python_client.egg-info/PKG-INFO
nightscout_python_client.egg-info/SOURCES.txt
nightscout_python_client.egg-info/dependency_links.txt
nightscout_python_client.egg-info/requires.txt
nightscout_python_client.egg-info/top_level.txt
nightscout_python_client/api/__init__.py
nightscout_python_client/api/debug_api.py
nightscout_python_client/api/devicestatus_api.py
nightscout_python_client/api/entries_api.py
nightscout_python_client/api/profile_api.py
nightscout_python_client/api/status_api.py
nightscout_python_client/api/treatments_api.py
nightscout_python_client/api/util.py
nightscout_python_client/models/__init__.py
nightscout_python_client/models/delete_status.py
nightscout_python_client/models/devicestatus.py
nightscout_python_client/models/devicestatuses.py
nightscout_python_client/models/entries.py
nightscout_python_client/models/entry.py
nightscout_python_client/models/error.py
nightscout_python_client/models/extended_settings.py
nightscout_python_client/models/mongo_query.py
nightscout_python_client/models/optime.py
nightscout_python_client/models/profile.py
nightscout_python_client/models/pump.py
nightscout_python_client/models/pumpbattery.py
nightscout_python_client/models/pumpstatus.py
nightscout_python_client/models/settings.py
nightscout_python_client/models/status.py
nightscout_python_client/models/threshold.py
nightscout_python_client/models/treatment.py
nightscout_python_client/models/treatments.py
nightscout_python_client/models/uploader.py
nightscout_python_client/models/xdripjs.py
test/__init__.py
test/test_debug_api.py
test/test_delete_status.py
test/test_devicestatus.py
test/test_devicestatus_api.py
test/test_devicestatuses.py
test/test_entries.py
test/test_entries_api.py
test/test_entry.py
test/test_error.py
test/test_extended_settings.py
test/test_mongo_query.py
test/test_optime.py
test/test_profile.py
test/test_profile_api.py
test/test_pump.py
test/test_pumpbattery.py
test/test_pumpstatus.py
test/test_settings.py
test/test_status.py
test/test_status_api.py
test/test_threshold.py
test/test_treatment.py
