Metadata-Version: 1.0
Name: nightscout-python-client
Version: 0.0.1
Summary: Nightscout Python Client
Home-page: https://github.com/erobinson/nightscout-python-client
Author: UNKNOWN
Author-email: Edward.R.Robinson@gmail.com
License: UNKNOWN
Keywords: Swagger,Nightscout API
Platform: UNKNOWN
